zap_toolkit/__init__.py
zap_toolkit/docs/tutorials/01_tutorial_crawl_passive.ipynb
zap_toolkit/tools/crawler.py
zap_toolkit/tools/pscanner.py
zap_toolkit/tools/session.py
zap_toolkit-0.0.3.dist-info/METADATA
zap_toolkit-0.0.3.dist-info/WHEEL
zap_toolkit-0.0.3.dist-info/RECORD
