Metadata-Version: 2.1
Name: zap_toolkit
Version: 0.0.3
Summary: Using ZAP API as tools in LLM-agentic systems
Author: Tomasz Salacinski
Author-email: tomasz.salacinski@sedivio.com
Requires-Python: >=3.12,<4.0
Classifier: Programming Language :: Python :: 3
Classifier: Programming Language :: Python :: 3.12
Classifier: Programming Language :: Python :: 3.13
Requires-Dist: langchain (>=0.3.7,<0.4.0)
Requires-Dist: pydantic (>=2.10.2,<3.0.0)
Requires-Dist: zaproxy (>=0.3.2,<0.4.0)
